jwst_gtvt/__init__.py
jwst_gtvt/constants.py
jwst_gtvt/display_results.py
jwst_gtvt/jwst_tvt.py
jwst_gtvt/plotting.py
jwst_gtvt/utils.py
jwst_gtvt/data/ephemeris_2021-12-26_2025-06-12.txt
jwst_gtvt/scripts/__init__.py
jwst_gtvt/scripts/create_new_ephemeris.py
jwst_gtvt/scripts/delete_cache.py
jwst_gtvt/scripts/jwst_gtvt.py
jwst_gtvt/scripts/jwst_mtvt.py
jwst_gtvt/tests/test_gtvt.py
jwst_gtvt-1.1.1.dist-info/licenses/LICENSE
jwst_gtvt-1.1.1.dist-info/METADATA
jwst_gtvt-1.1.1.dist-info/WHEEL
jwst_gtvt-1.1.1.dist-info/entry_points.txt
jwst_gtvt-1.1.1.dist-info/top_level.txt
jwst_gtvt-1.1.1.dist-info/RECORD
