Metadata-Version: 2.4
Name: jwst_gtvt
Version: 1.1.1
Summary: JWST General and Moving Target Visibility Tool
Author: Mees Fix, Bryan Holler, Matthew Hill
License: Copyright (C) 2019 Association of Universities for Research in Astronomy (AURA)
Keywords: astronomy,python
Classifier: Programming Language :: Python
Requires-Python: >=3.10
License-File: LICENSE
Requires-Dist: astropy>=5.2.2
Requires-Dist: astroquery>=0.4.6
Requires-Dist: docopt>=0.6.2
Requires-Dist: matplotlib>=3.7.1
Requires-Dist: numpy>=1.24.3
Requires-Dist: pysiaf>=0.19.0
Requires-Dist: pandas>=2.0.1
Requires-Dist: docopt>=0.6.2
Requires-Dist: tabulate>=0.9.0
Provides-Extra: test
Requires-Dist: pytest; extra == "test"
Requires-Dist: pytest-cov; extra == "test"
Provides-Extra: docs
Requires-Dist: sphinx; extra == "docs"
Requires-Dist: sphinx_rtd_theme; extra == "docs"
Requires-Dist: stsci_rtd_theme; extra == "docs"
Dynamic: license-file
